condiga-0.2.2.data/data/LICENSE
condiga-0.2.2.data/data/README.md
condiga-0.2.2.data/scripts/condiga
condiga_utils/__init__.py
condiga_utils/contig_utils.py
condiga_utils/coverage_utils.py
condiga_utils/gene_utils.py
condiga_utils/genome_utils.py
condiga_utils/species_utils.py
condiga_utils/taxa_utils.py
condiga_utils/support/convert.py
condiga-0.2.2.dist-info/LICENSE
condiga-0.2.2.dist-info/METADATA
condiga-0.2.2.dist-info/WHEEL
condiga-0.2.2.dist-info/entry_points.txt
condiga-0.2.2.dist-info/top_level.txt
condiga-0.2.2.dist-info/zip-safe
condiga-0.2.2.dist-info/RECORD
