Metadata-Version: 2.1
Name: condiga
Version: 0.2.2
Summary: ConDiGA: Contigs directed gene annotation for accurate protein sequence database construction in metaproteomics
Home-page: https://github.com/metagentools/ConDiGA
Author: Vijini Mallawaarachchi and Yu Lin
Author-email: viji.mallawaarachchi@gmail.com
License: MIT
Classifier: Development Status :: 4 - Beta
Classifier: Programming Language :: Python :: 3
Classifier: License :: OSI Approved :: MIT License
Classifier: Natural Language :: English
Classifier: Topic :: Scientific/Engineering :: Bio-Informatics
Classifier: Operating System :: OS Independent
Requires-Python: >=3.8
License-File: LICENSE
Requires-Dist: biopython
Requires-Dist: tqdm
Requires-Dist: XlsxWriter
Requires-Dist: click
